hdn/main.py
hdn-0.0.1.dist-info/LICENSE
hdn-0.0.1.dist-info/METADATA
hdn-0.0.1.dist-info/WHEEL
hdn-0.0.1.dist-info/entry_points.txt
hdn-0.0.1.dist-info/RECORD
