Metadata-Version: 2.1
Name: hdn
Version: 0.0.1
Summary: A Python CLI program to send messages to D-Bus
License: MIT
Author: Joe Doss
Author-email: joe@solidadmin.com
Requires-Python: >=3.11,<4.0
Classifier: License :: OSI Approved :: MIT License
Classifier: Programming Language :: Python :: 3
Classifier: Programming Language :: Python :: 3.11
Requires-Dist: jeepney (>=0.8.0,<0.9.0)
Requires-Dist: rich (>=13.5.2,<14.0.0)
Requires-Dist: typer[all] (>=0.9.0,<0.10.0)
